chuk_ai_session_manager/__init__.py
chuk_ai_session_manager/exceptions.py
chuk_ai_session_manager/infinite_conversation.py
chuk_ai_session_manager/sample_tools.py
chuk_ai_session_manager/session_aware_tool_processor.py
chuk_ai_session_manager/session_manager.py
chuk_ai_session_manager/session_prompt_builder.py
chuk_ai_session_manager/session_storage.py
chuk_ai_session_manager/api/__init__.py
chuk_ai_session_manager/api/simple_api.py
chuk_ai_session_manager/models/__init__.py
chuk_ai_session_manager/models/event_source.py
chuk_ai_session_manager/models/event_type.py
chuk_ai_session_manager/models/session.py
chuk_ai_session_manager/models/session_event.py
chuk_ai_session_manager/models/session_metadata.py
chuk_ai_session_manager/models/session_run.py
chuk_ai_session_manager/models/token_usage.py
chuk_ai_session_manager-0.7.dist-info/METADATA
chuk_ai_session_manager-0.7.dist-info/WHEEL
chuk_ai_session_manager-0.7.dist-info/top_level.txt
chuk_ai_session_manager-0.7.dist-info/RECORD
