Metadata-Version: 2.4
Name: chuk-ai-session-manager
Version: 0.7
Summary: Session manager for AI applications
Requires-Python: >=3.11
Requires-Dist: chuk-sessions>=0.4.1
Requires-Dist: chuk-tool-processor>=0.4.1
Requires-Dist: pydantic>=2.11.3
Provides-Extra: redis
Requires-Dist: chuk-sessions[redis]>=0.4.1; extra == "redis"
Requires-Dist: redis>=4.0.0; extra == "redis"
Provides-Extra: tiktoken
Requires-Dist: tiktoken>=0.9.0; extra == "tiktoken"
Provides-Extra: dev
Requires-Dist: pytest>=7.0.0; extra == "dev"
Requires-Dist: pytest-cov>=4.0.0; extra == "dev"
Requires-Dist: pytest-asyncio>=0.21.0; extra == "dev"
Requires-Dist: black>=23.0.0; extra == "dev"
Requires-Dist: isort>=5.12.0; extra == "dev"
Requires-Dist: mypy>=1.0.0; extra == "dev"
Provides-Extra: all
Requires-Dist: chuk-sessions[redis]>=0.4; extra == "all"
Requires-Dist: redis>=4.0.0; extra == "all"
Requires-Dist: tiktoken>=0.9.0; extra == "all"
